parserito/__init__.py
parserito/run.py
parserito-0.1.0.dist-info/LICENSE
parserito-0.1.0.dist-info/METADATA
parserito-0.1.0.dist-info/WHEEL
parserito-0.1.0.dist-info/top_level.txt
parserito-0.1.0.dist-info/RECORD
