Metadata-Version: 2.1
Name: parserito
Version: 0.1.0
Summary: A package to run tests from a yaml file.
Home-page: https://github.com/andres-root/parserito
Author: Andres Lujan
Author-email: andreslujandev@gmail.com
License-File: LICENSE
Requires-Dist: pyyaml
